{
	"content": [
		{
			"id": "5fea8395",
			"settings": [],
			"elements": [
				{
					"id": "1c729595",
					"settings": {
						"__dynamic__": {
							"image": "[elementor-tag id=\"\" name=\"post-featured-image\" settings=\"%7B%22fallback%22%3A%7B%22url%22%3A%22%22%2C%22id%22%3A%22%22%2C%22size%22%3A%22%22%7D%7D\"]"
						},
						"height": { "unit": "px", "size": 400, "sizes": [] }
					},
					"elements": [],
					"isInner": false,
					"widgetType": "theme-post-featured-image",
					"elType": "widget"
				},
				{
					"id": "6aa9e207",
					"settings": {
						"__dynamic__": {
							"title": "[elementor-tag id=\"\" name=\"post-title\" settings=\"%7B%22before%22%3A%22%22%2C%22after%22%3A%22%22%2C%22fallback%22%3A%22%22%7D\"]"
						},
						"title": "Add Your Heading Text Here",
						"header_size": "h3"
					},
					"elements": [],
					"isInner": false,
					"widgetType": "theme-post-title",
					"elType": "widget"
				},
				{
					"id": "5a404c98",
					"settings": {
						"title": "Add Your Heading Text Here",
						"header_size": "h5",
						"__dynamic__": {
							"title": "[elementor-tag id=\"d10a36c\" name=\"surecart-price-amount\" settings=\"%7B%7D\"]"
						}
					},
					"elements": [],
					"isInner": false,
					"widgetType": "heading",
					"elType": "widget"
				}
			],
			"isInner": false,
			"elType": "container"
		}
	],
	"page_settings": [],
	"version": "0.4",
	"title": "SureCart Loop Item Template",
	"type": "loop-item"
}
