{
	"$schema": "https://schemas.wp.org/trunk/block.json",
	"apiVersion": 3,
	"name": "surecart/product-selected-price-interval",
	"title": "Interval",
	"description": "Displays the currently selected price interval.",
	"version": "1.0.0",
	"category": "widgets",
	"icon": "clock",
	"ancestor": ["surecart/product-page"],
	"example": {
		"attributes": {}
	},
	"supports": {
		"interactivity": true,
		"color": {
			"gradients": true,
			"text": true,
			"background": false,
			"__experimentalDefaultControls": {
				"text": true,
				"button": true
			}
		},
		"typography": {
			"fontSize": true,
			"lineHeight": true
		}
	},
	"textdomain": "surecart",
	"render": "file:./view.php",
	"editorScript": "file:./index.js",
	"viewScriptModule": ["@surecart/product-page"]
}
