{
	"apiVersion": 2,
	"name": "surecart/product-collection-description",
	"title": "Product Collection Description",
	"description": "Display the product collection description",
	"category": "surecart",
	"keywords": ["description"],
	"supports": {
		"reusable": false,
		"html": false,
		"multiple": false,
		"layout": true,
		"color": {
			"gradients": true,
			"link": false,
			"__experimentalDefaultControls": {
				"background": true,
				"text": true,
				"link": true
			}
		},
		"typography": {
			"fontSize": true,
			"lineHeight": true,
			"__experimentalFontFamily": true,
			"__experimentalFontWeight": true,
			"__experimentalFontStyle": true,
			"__experimentalTextTransform": true,
			"__experimentalTextDecoration": true,
			"__experimentalLetterSpacing": true,
			"__experimentalDefaultControls": {
				"fontSize": true,
				"fontAppearance": true,
				"textTransform": true
			}
		}
	}
}
